{
  "main": {
    "id": "c2aa961d58cf48b1",
    "type": "split",
    "children": [
      {
        "id": "3761bb61e18c59ac",
        "type": "tabs",
        "children": [
          {
            "id": "bf160684a11d43a1",
            "type": "leaf",
            "pane-relief:history-v1": {
              "pos": 0,
              "stack": [
                {
                  "state": "{}",
                  "eState": "{}"
                },
                {
                  "title": "Lorin",
                  "icon": "lucide-file",
                  "state": "{\"type\":\"markdown\",\"state\":{\"file\":\"Lendis/Locations/Lorin.md\",\"mode\":\"source\",\"source\":true}}",
                  "eState": "{\"cursor\":{\"from\":{\"line\":0,\"ch\":0},\"to\":{\"line\":0,\"ch\":0}}}"
                },
                {
                  "title": "Choir Gods",
                  "icon": "lucide-file",
                  "state": "{\"type\":\"markdown\",\"state\":{\"file\":\"Lendis/Religion/The Heavenly Choir/Choir Gods.md\",\"mode\":\"preview\",\"source\":true}}",
                  "eState": "{\"scroll\":0}"
                },
                {
                  "title": "Lorin",
                  "icon": "lucide-file",
                  "state": "{\"type\":\"markdown\",\"state\":{\"file\":\"Lendis/Locations/Lorin.md\",\"mode\":\"source\",\"source\":true}}",
                  "eState": "{\"cursor\":{\"from\":{\"line\":28,\"ch\":232},\"to\":{\"line\":28,\"ch\":232}},\"scroll\":16.33615451388889}"
                },
                {
                  "title": "Choir Gods",
                  "icon": "lucide-file",
                  "state": "{\"type\":\"markdown\",\"state\":{\"file\":\"Lendis/Religion/The Heavenly Choir/Choir Gods.md\",\"mode\":\"source\",\"source\":true}}",
                  "eState": "{\"cursor\":{\"from\":{\"line\":2,\"ch\":15},\"to\":{\"line\":2,\"ch\":15}}}"
                },
                {
                  "title": "The Made Gods",
                  "icon": "lucide-file",
                  "state": "{\"type\":\"markdown\",\"state\":{\"file\":\"Lendis/Religion/Made Gods/The Made Gods.md\",\"mode\":\"source\",\"source\":true}}",
                  "eState": "{\"cursor\":{\"from\":{\"line\":0,\"ch\":0},\"to\":{\"line\":0,\"ch\":0}}}"
                },
                {
                  "title": "Choir Gods",
                  "icon": "lucide-file",
                  "state": "{\"type\":\"markdown\",\"state\":{\"file\":\"Lendis/Religion/The Heavenly Choir/Choir Gods.md\",\"mode\":\"source\",\"source\":true}}",
                  "eState": "{\"cursor\":{\"from\":{\"line\":2,\"ch\":0},\"to\":{\"line\":2,\"ch\":0}}}"
                },
                {
                  "title": "The Made Gods",
                  "icon": "lucide-file",
                  "state": "{\"type\":\"markdown\",\"state\":{\"file\":\"Lendis/Religion/Made Gods/The Made Gods.md\",\"mode\":\"source\",\"source\":true}}",
                  "eState": "{\"cursor\":{\"from\":{\"line\":0,\"ch\":0},\"to\":{\"line\":0,\"ch\":0}}}"
                },
                {
                  "title": "Choir Gods",
                  "icon": "lucide-file",
                  "state": "{\"type\":\"markdown\",\"state\":{\"file\":\"Lendis/Religion/The Heavenly Choir/Choir Gods.md\",\"mode\":\"source\",\"source\":true}}",
                  "eState": "{\"cursor\":{\"from\":{\"line\":0,\"ch\":307},\"to\":{\"line\":0,\"ch\":307}}}"
                },
                {
                  "title": "The Heavenly Choir",
                  "icon": "lucide-file",
                  "state": "{\"type\":\"markdown\",\"state\":{\"file\":\"Lendis/Religion/The Heavenly Choir/The Heavenly Choir.md\",\"mode\":\"source\",\"source\":true}}",
                  "eState": "{\"cursor\":{\"from\":{\"line\":1,\"ch\":0},\"to\":{\"line\":1,\"ch\":0}}}"
                },
                {
                  "title": "Nightmare Cults",
                  "icon": "lucide-file",
                  "state": "{\"type\":\"markdown\",\"state\":{\"file\":\"Lendis/Religion/Nightmare Cults.md\",\"mode\":\"source\",\"source\":true}}",
                  "eState": "{\"cursor\":{\"from\":{\"line\":0,\"ch\":0},\"to\":{\"line\":0,\"ch\":0}}}"
                },
                {
                  "title": "The Heavenly Choir",
                  "icon": "lucide-file",
                  "state": "{\"type\":\"markdown\",\"state\":{\"file\":\"Lendis/Religion/The Heavenly Choir/The Heavenly Choir.md\",\"mode\":\"source\",\"source\":true}}",
                  "eState": "{\"cursor\":{\"from\":{\"line\":0,\"ch\":0},\"to\":{\"line\":0,\"ch\":0}}}"
                },
                {
                  "title": "The Made Gods",
                  "icon": "lucide-file",
                  "state": "{\"type\":\"markdown\",\"state\":{\"file\":\"Lendis/Religion/Made Gods/The Made Gods.md\",\"mode\":\"source\",\"source\":true}}",
                  "eState": "{\"cursor\":{\"from\":{\"line\":0,\"ch\":0},\"to\":{\"line\":0,\"ch\":0}}}"
                },
                {
                  "title": "The Heavenly Choir",
                  "icon": "lucide-file",
                  "state": "{\"type\":\"markdown\",\"state\":{\"file\":\"Lendis/Religion/The Heavenly Choir/The Heavenly Choir.md\",\"mode\":\"source\",\"source\":true}}",
                  "eState": "{\"cursor\":{\"from\":{\"line\":0,\"ch\":0},\"to\":{\"line\":0,\"ch\":0}},\"scroll\":0}"
                },
                {
                  "title": "Lorin",
                  "icon": "lucide-file",
                  "state": "{\"type\":\"markdown\",\"state\":{\"file\":\"Lendis/Locations/Lorin.md\",\"mode\":\"source\",\"source\":true}}",
                  "eState": "{\"cursor\":{\"from\":{\"line\":28,\"ch\":232},\"to\":{\"line\":28,\"ch\":232}},\"scroll\":18.670052083333335}"
                },
                {
                  "title": "The Heavenly Choir",
                  "icon": "lucide-file",
                  "state": "{\"type\":\"markdown\",\"state\":{\"file\":\"Lendis/Religion/The Heavenly Choir/The Heavenly Choir.md\",\"mode\":\"source\",\"source\":true}}",
                  "eState": "{\"cursor\":{\"from\":{\"line\":2,\"ch\":14},\"to\":{\"line\":2,\"ch\":14}},\"scroll\":0}"
                },
                {
                  "title": "Lorin",
                  "icon": "lucide-file",
                  "state": "{\"type\":\"markdown\",\"state\":{\"file\":\"Lendis/Locations/Lorin.md\",\"mode\":\"source\",\"source\":true}}",
                  "eState": "{\"cursor\":{\"from\":{\"line\":28,\"ch\":139},\"to\":{\"line\":28,\"ch\":139}},\"scroll\":18.553385416666668}"
                },
                {
                  "title": "Thaxhold",
                  "icon": "lucide-file",
                  "state": "{\"type\":\"markdown\",\"state\":{\"file\":\"Lendis/Locations/Thaxhold.md\",\"mode\":\"source\",\"source\":true}}",
                  "eState": "{\"cursor\":{\"from\":{\"line\":0,\"ch\":0},\"to\":{\"line\":0,\"ch\":0}},\"scroll\":25.396744791666666}"
                },
                {
                  "title": "The Heavenly Choir",
                  "icon": "lucide-file",
                  "state": "{\"type\":\"markdown\",\"state\":{\"file\":\"Lendis/Religion/The Heavenly Choir/The Heavenly Choir.md\",\"mode\":\"source\",\"source\":true}}",
                  "eState": "{\"cursor\":{\"from\":{\"line\":0,\"ch\":475},\"to\":{\"line\":0,\"ch\":475}},\"scroll\":0}"
                },
                {
                  "title": "Lorin",
                  "icon": "lucide-file",
                  "state": "{\"type\":\"markdown\",\"state\":{\"file\":\"Lendis/Locations/Lorin.md\",\"mode\":\"source\",\"source\":true}}",
                  "eState": "{\"cursor\":{\"from\":{\"line\":28,\"ch\":0},\"to\":{\"line\":28,\"ch\":0}},\"scroll\":21.650390625}"
                },
                {
                  "title": "Uncommon Weapons",
                  "icon": "lucide-file",
                  "state": "{\"type\":\"markdown\",\"state\":{\"file\":\"Lendis/Uncommon Weapons.md\",\"mode\":\"source\",\"source\":true}}",
                  "eState": "{\"cursor\":{\"from\":{\"line\":0,\"ch\":0},\"to\":{\"line\":0,\"ch\":0}},\"scroll\":0}"
                },
                {
                  "title": "Mechanics",
                  "icon": "lucide-file",
                  "state": "{\"type\":\"markdown\",\"state\":{\"file\":\"Lendis/Mechanics.md\",\"mode\":\"source\",\"source\":true}}",
                  "eState": "{\"cursor\":{\"from\":{\"line\":0,\"ch\":0},\"to\":{\"line\":0,\"ch\":0}},\"scroll\":0}"
                },
                {
                  "title": "Lorin",
                  "icon": "lucide-file",
                  "state": "{\"type\":\"markdown\",\"state\":{\"file\":\"Lendis/Locations/Lorin.md\",\"mode\":\"source\",\"source\":true}}",
                  "eState": "{\"cursor\":{\"from\":{\"line\":16,\"ch\":0},\"to\":{\"line\":16,\"ch\":0}},\"scroll\":7.916666666666667}"
                },
                {
                  "title": "Zhorhold",
                  "icon": "lucide-file",
                  "state": "{\"type\":\"markdown\",\"state\":{\"file\":\"Lendis/Locations/Zhorhold.md\",\"mode\":\"source\",\"source\":true}}",
                  "eState": "{\"cursor\":{\"from\":{\"line\":0,\"ch\":0},\"to\":{\"line\":0,\"ch\":0}}}"
                },
                {
                  "title": "Lorin",
                  "icon": "lucide-file",
                  "state": "{\"type\":\"markdown\",\"state\":{\"file\":\"Lendis/Locations/Lorin.md\",\"mode\":\"source\",\"source\":true}}",
                  "eState": "{\"cursor\":{\"from\":{\"line\":10,\"ch\":75},\"to\":{\"line\":10,\"ch\":75}},\"scroll\":0}"
                },
                {
                  "title": "Zhorhold",
                  "icon": "lucide-file",
                  "state": "{\"type\":\"markdown\",\"state\":{\"file\":\"Lendis/Locations/Zhorhold.md\",\"mode\":\"source\",\"source\":true}}",
                  "eState": "{\"cursor\":{\"from\":{\"line\":13,\"ch\":184},\"to\":{\"line\":13,\"ch\":184}},\"scroll\":0.8771929824561403}"
                },
                {
                  "title": "Lorin",
                  "icon": "lucide-file",
                  "state": "{\"type\":\"markdown\",\"state\":{\"file\":\"Lendis/Locations/Lorin.md\",\"mode\":\"source\",\"source\":true}}",
                  "eState": "{\"cursor\":{\"from\":{\"line\":10,\"ch\":54},\"to\":{\"line\":10,\"ch\":54}}}"
                },
                {
                  "title": "Marksgrav",
                  "icon": "lucide-file",
                  "state": "{\"type\":\"markdown\",\"state\":{\"file\":\"Lendis/Locations/Marksgrav.md\",\"mode\":\"source\",\"source\":true}}",
                  "eState": "{\"cursor\":{\"from\":{\"line\":0,\"ch\":0},\"to\":{\"line\":0,\"ch\":0}}}"
                },
                {
                  "title": "Lorin",
                  "icon": "lucide-file",
                  "state": "{\"type\":\"markdown\",\"state\":{\"file\":\"Lendis/Locations/Lorin.md\",\"mode\":\"source\",\"source\":true}}",
                  "eState": "{\"cursor\":{\"from\":{\"line\":10,\"ch\":0},\"to\":{\"line\":10,\"ch\":0}},\"scroll\":0}"
                },
                {
                  "title": "Zhorhold",
                  "icon": "lucide-file",
                  "state": "{\"type\":\"markdown\",\"state\":{\"file\":\"Lendis/Locations/Zhorhold.md\",\"mode\":\"source\",\"source\":true}}",
                  "eState": "{\"cursor\":{\"from\":{\"line\":0,\"ch\":0},\"to\":{\"line\":0,\"ch\":0}},\"scroll\":0.8771929824561403}"
                },
                {
                  "title": "Lorin",
                  "icon": "lucide-file",
                  "state": "{\"type\":\"markdown\",\"state\":{\"file\":\"Lendis/Locations/Lorin.md\",\"mode\":\"source\",\"source\":true}}",
                  "eState": "{\"cursor\":{\"from\":{\"line\":10,\"ch\":0},\"to\":{\"line\":10,\"ch\":0}}}"
                },
                {
                  "title": "Watcher of Night",
                  "icon": "lucide-file",
                  "state": "{\"type\":\"markdown\",\"state\":{\"file\":\"Lendis/Cultural Archetypes/Watcher of Night.md\",\"mode\":\"source\",\"source\":true}}",
                  "eState": "{\"cursor\":{\"from\":{\"line\":49,\"ch\":269},\"to\":{\"line\":49,\"ch\":269}},\"scroll\":0}"
                },
                {
                  "title": "pf2e-1-action",
                  "icon": "lucide-file",
                  "state": "{\"type\":\"markdown\",\"state\":{\"file\":\"Templates/pf2e-1-action.md\",\"mode\":\"source\",\"source\":true}}",
                  "eState": "{\"cursor\":{\"from\":{\"line\":0,\"ch\":0},\"to\":{\"line\":0,\"ch\":0}}}"
                },
                {
                  "title": "PF2e - Format Font - Level Highlight",
                  "icon": "lucide-file",
                  "state": "{\"type\":\"markdown\",\"state\":{\"file\":\"Templates/PF2e - Format Font - Level Highlight.md\",\"mode\":\"source\",\"source\":true}}",
                  "eState": "{\"cursor\":{\"from\":{\"line\":0,\"ch\":0},\"to\":{\"line\":0,\"ch\":0}}}"
                },
                {
                  "title": "pf2e-reaction",
                  "icon": "lucide-file",
                  "state": "{\"type\":\"markdown\",\"state\":{\"file\":\"Templates/pf2e-reaction.md\",\"mode\":\"source\",\"source\":true}}",
                  "eState": "{\"cursor\":{\"from\":{\"line\":0,\"ch\":0},\"to\":{\"line\":0,\"ch\":0}},\"scroll\":0}"
                },
                {
                  "title": "Watcher of Night",
                  "icon": "lucide-file",
                  "state": "{\"type\":\"markdown\",\"state\":{\"file\":\"Lendis/Cultural Archetypes/Watcher of Night.md\",\"mode\":\"preview\",\"source\":true}}",
                  "eState": "{\"scroll\":21.09090909090909}"
                },
                {
                  "title": "Lendis",
                  "icon": "lucide-file",
                  "state": "{\"type\":\"markdown\",\"state\":{\"file\":\"Lendis/Lendis.md\",\"mode\":\"preview\",\"source\":true}}",
                  "eState": "{\"scroll\":0}"
                },
                {
                  "title": "Ravidhold",
                  "icon": "lucide-file",
                  "state": "{\"type\":\"markdown\",\"state\":{\"file\":\"Lendis/Locations/Ravidhold.md\",\"mode\":\"source\",\"source\":true}}",
                  "eState": "{\"cursor\":{\"from\":{\"line\":0,\"ch\":0},\"to\":{\"line\":0,\"ch\":0}},\"scroll\":32.68359375}"
                }
              ]
            },
            "state": {
              "type": "markdown",
              "state": {
                "file": "Lendis/Lendis.md",
                "mode": "preview",
                "source": true
              }
            }
          }
        ]
      }
    ],
    "direction": "vertical"
  },
  "left": {
    "id": "e432da0fe150becf",
    "type": "split",
    "children": [
      {
        "id": "8939e3e1b87ca13f",
        "type": "tabs",
        "children": [
          {
            "id": "930586ea075b4819",
            "type": "leaf",
            "pane-relief:history-v1": {
              "pos": 0,
              "stack": [
                {
                  "state": "{}",
                  "eState": "{}"
                }
              ]
            },
            "state": {
              "type": "file-explorer",
              "state": {
                "sortOrder": "alphabetical"
              }
            }
          },
          {
            "id": "d21901b2754d3523",
            "type": "leaf",
            "pane-relief:history-v1": {
              "pos": 0,
              "stack": [
                {
                  "state": "{}",
                  "eState": "{}"
                }
              ]
            },
            "state": {
              "type": "search",
              "state": {
                "query": "",
                "matchingCase": false,
                "explainSearch": false,
                "collapseAll": false,
                "extraContext": false,
                "sortOrder": "alphabetical"
              }
            }
          },
          {
            "id": "72309ade21ea7ff9",
            "type": "leaf",
            "pane-relief:history-v1": {
              "pos": 0,
              "stack": [
                {
                  "state": "{}",
                  "eState": "{}"
                }
              ]
            },
            "state": {
              "type": "bookmarks",
              "state": {}
            }
          }
        ]
      }
    ],
    "direction": "horizontal",
    "width": 300
  },
  "right": {
    "id": "1538d94f79e1a140",
    "type": "split",
    "children": [
      {
        "id": "9b1cd5cc7876872c",
        "type": "tabs",
        "children": [
          {
            "id": "bdf1141601d84d2e",
            "type": "leaf",
            "pane-relief:history-v1": {
              "pos": 0,
              "stack": [
                {
                  "state": "{}",
                  "eState": "{}"
                }
              ]
            },
            "state": {
              "type": "backlink",
              "state": {
                "file": "Lendis/Lendis.md",
                "collapseAll": false,
                "extraContext": false,
                "sortOrder": "alphabetical",
                "showSearch": false,
                "searchQuery": "",
                "backlinkCollapsed": false,
                "unlinkedCollapsed": true
              }
            }
          },
          {
            "id": "ca090d87ba05d12a",
            "type": "leaf",
            "pane-relief:history-v1": {
              "pos": 0,
              "stack": [
                {
                  "state": "{}",
                  "eState": "{}"
                }
              ]
            },
            "state": {
              "type": "outgoing-link",
              "state": {
                "file": "Lendis/Lendis.md",
                "linksCollapsed": false,
                "unlinkedCollapsed": true
              }
            }
          },
          {
            "id": "60f6349f7f36a197",
            "type": "leaf",
            "pane-relief:history-v1": {
              "pos": 0,
              "stack": [
                {
                  "state": "{}",
                  "eState": "{}"
                }
              ]
            },
            "state": {
              "type": "tag",
              "state": {
                "sortOrder": "frequency",
                "useHierarchy": false
              }
            }
          },
          {
            "id": "c55340d9c2573662",
            "type": "leaf",
            "pane-relief:history-v1": {
              "pos": 0,
              "stack": [
                {
                  "state": "{}",
                  "eState": "{}"
                }
              ]
            },
            "state": {
              "type": "outline",
              "state": {
                "file": "Lendis/Lendis.md"
              }
            }
          },
          {
            "id": "f950d8a37bb3023d",
            "type": "leaf",
            "pane-relief:history-v1": {
              "pos": 0,
              "stack": [
                {
                  "state": "{}",
                  "eState": "{}"
                }
              ]
            },
            "state": {
              "type": "BC-matrix",
              "state": {}
            }
          },
          {
            "id": "af80a77afc303655",
            "type": "leaf",
            "pane-relief:history-v1": {
              "pos": 0,
              "stack": [
                {
                  "state": "{}",
                  "eState": "{}"
                }
              ]
            },
            "state": {
              "type": "BC-tree",
              "state": {}
            }
          },
          {
            "id": "db4c886e1b77fb8a",
            "type": "leaf",
            "pane-relief:history-v1": {
              "pos": 0,
              "stack": [
                {
                  "state": "{}",
                  "eState": "{}"
                }
              ]
            },
            "state": {
              "type": "DICE_ROLLER_VIEW",
              "state": {}
            }
          },
          {
            "id": "b5e7b1450f8b6bc5",
            "type": "leaf",
            "pane-relief:history-v1": {
              "pos": 0,
              "stack": [
                {
                  "state": "{}",
                  "eState": "{}"
                }
              ]
            },
            "state": {
              "type": "FANTASY_CALENDAR",
              "state": {}
            }
          },
          {
            "id": "521fc6862ef45513",
            "type": "leaf",
            "pane-relief:history-v1": {
              "pos": 0,
              "stack": [
                {
                  "state": "{}",
                  "eState": "{}"
                }
              ]
            },
            "state": {
              "type": "initiative-tracker-view",
              "state": {}
            }
          }
        ],
        "currentTab": 1
      }
    ],
    "direction": "horizontal",
    "width": 300
  },
  "left-ribbon": {
    "hiddenItems": {
      "switcher:Open quick switcher": false,
      "graph:Open graph view": false,
      "canvas:Create new canvas": false,
      "daily-notes:Open today's daily note": false,
      "templates:Insert template": false,
      "command-palette:Open command palette": false,
      "table-editor-obsidian:Advanced Tables Toolbar": false,
      "obsidian-excalidraw-plugin:Create new drawing": false,
      "fantasy-calendar:Open Large Fantasy Calendar": false,
      "initiative-tracker:Intiative Tracker Encounter Builder": false,
      "obsidian-leaflet-plugin:Open Leaflet Map": false,
      "breadcrumbs:Breadcrumbs Visualisation": false
    }
  },
  "active": "bf160684a11d43a1",
  "lastOpenFiles": [
    "world-of-lendis",
    "package.json",
    "Lendis/Religion/The Heavenly Choir/Choir Gods.md",
    "Lendis/Locations/Lorin.md",
    "Lendis/Religion/Made Gods/The Made Gods.md",
    "Lendis/Religion/The Heavenly Choir/The Heavenly Choir.md",
    "Lendis/Religion/Nightmare Cults.md",
    "Lendis/Religion/The Heavenly Choir",
    "Lendis/Locations/Thaxhold.md",
    "Lendis/Uncommon Weapons.md",
    "Lendis/Mechanics.md",
    "Lendis/Locations/Zhorhold.md",
    "Lendis/Locations/Marksgrav.md",
    "Lendis/Cultural Archetypes/Watcher of Night.md",
    "Lendis/Cultural Archetypes/Elemental Court.md",
    "Templates/pf2e-1-action.md",
    "Templates/PF2e - Format Font - Level Highlight.md",
    "Templates/pf2e-reaction.md",
    "Lendis/Lendis.md",
    "Lendis/Locations/Ravidhold.md",
    "Lendis/Locations/Drakhold.md",
    "Lendis/Locations/Voristed.md",
    "Lendis/The Nightmare.md",
    "Lendis/Locations/Worldbirth Mountains.md",
    "Lendis/Locations/Immortal Isle.md",
    "the Militia.md",
    "Lendis/Religion/The Living Stone.md",
    "Lendis/Cultural Archetypes/Stone Bound.md",
    "Lendis/Religion/Made Gods",
    "Lendis/People",
    "Lendis.jpg",
    "Lendis/Locations",
    "Lendis",
    "Templates",
    "Lendis/Cultural Archetypes",
    "Lendis/Religion/Elemental Lords",
    "Lendis/Religion/The Dragon Ideal",
    "Pathfinder-2E-SRD-Markdown-main/Bestiary/_attachments/pf2e-settlement.png",
    "Pathfinder-2E-SRD-Markdown-main/Bestiary/_attachments/pf2e-quest.png",
    "Pathfinder-2E-SRD-Markdown-main/Bestiary/_attachments/pf2e-quest-icon.png",
    "Pathfinder-2E-SRD-Markdown-main/Bestiary/_attachments/pf2e-influence.png",
    "Pathfinder-2E-SRD-Markdown-main/Bestiary/_attachments/pf2e-misc.png",
    "Pathfinder-2E-SRD-Markdown-main/Bestiary/_attachments/pf2e-hazard.png",
    "Pathfinder-2E-SRD-Markdown-main/Bestiary/_attachments/pf2e-action.png"
  ]
}